mzmlripper/__init__.py
mzmlripper/chromatograms.py
mzmlripper/extractor.py
mzmlripper/logger.py
mzmlripper/mzml_parser.py
mzmlripper/spectrum.py
mzmlripper/splash_helpers.py
mzmlripper-1.3.1.dist-info/LICENSE
mzmlripper-1.3.1.dist-info/METADATA
mzmlripper-1.3.1.dist-info/WHEEL
mzmlripper-1.3.1.dist-info/top_level.txt
mzmlripper-1.3.1.dist-info/RECORD
