Metadata-Version: 2.1
Name: mzmlripper
Version: 1.3.1
Summary: Extractor for MS1-MS4 level spectra from mzML file format
Home-page: https://github.com/croningp/mzmlripper
Author: Cronin Group
Author-email: croningp.pypi@gmail.com
License: UNKNOWN
Platform: UNKNOWN
Classifier: Programming Language :: Python :: 3
Classifier: License :: OSI Approved :: MIT License
Classifier: Operating System :: OS Independent
Requires-Python: >=3.6
